Metadata-Version: 1.0
Name: kkpy-gaussbinomial
Version: 1.0
Summary: Gaussian/binomial distributions
Home-page: UNKNOWN
Author: Kamila Kolpashnikova
Author-email: kamilakolpashnikova@gmail.com
License: UNKNOWN
Platform: UNKNOWN
